terminalfun.py
terminal_fun-0.0.1.dist-info/LICENSE.txt
terminal_fun-0.0.1.dist-info/METADATA
terminal_fun-0.0.1.dist-info/WHEEL
terminal_fun-0.0.1.dist-info/top_level.txt
terminal_fun-0.0.1.dist-info/RECORD
